[
  {
    "FullName": "Cairo Festival City Cinema",
    "Logo": "https://th.bing.com/th/id/R.40f697a1017c6d64c7c48ca6566e1ace?rik=zYq5RK3yBNZyWg&pid=ImgRaw&r=0",
    "Description": "A modern cinema complex with 17 screens, offering the latest movies in various genres and languages."
  },
  {
    "FullName": "Zawya Cinema",
    "Logo": "https://th.bing.com/th/id/OIP.PcPKuDyABOT0RnAZ6H7y-gHaHa?rs=1&pid=ImgDetMain",
    "Description": "An independent cinema that showcases alternative and artistic films from Egypt and the region, as well as hosting festivals and events."
  },
  {
    "FullName": "Galaxy Cinema",
    "Logo": "https://th.bing.com/th/id/OIP.GzIRwPaeanDGnqchzrF8dAHaHa?rs=1&pid=ImgDetMain",
    "Description": "A popular cinema chain with multiple branches across the country, featuring comfortable seats, high-quality sound and picture, and a variety of snacks and beverages."
  }
]

